flask_ask_youtube/__init__.py
flask_ask_youtube/cache.py
flask_ask_youtube/convert.py
flask_ask_youtube/core.py
flask_ask_youtube/models.py
flask_ask_youtube/verifier.py
flask_ask_youtube-1.9.8.dist-info/LICENSE.txt
flask_ask_youtube-1.9.8.dist-info/METADATA
flask_ask_youtube-1.9.8.dist-info/WHEEL
flask_ask_youtube-1.9.8.dist-info/top_level.txt
flask_ask_youtube-1.9.8.dist-info/RECORD
